recall/__init__.py
recall/recall_base.py
recall/recall_custom.py
recall/recall_official.py
macroscopic_recall-0.1.0.dist-info/METADATA
macroscopic_recall-0.1.0.dist-info/WHEEL
macroscopic_recall-0.1.0.dist-info/top_level.txt
macroscopic_recall-0.1.0.dist-info/RECORD
